pyvcell/__init__.py
pyvcell/_internal/__init__.py
pyvcell/_internal/api/__init__.py
pyvcell/_internal/api/vcell_client/__init__.py
pyvcell/_internal/api/vcell_client/api/__init__.py
pyvcell/_internal/api/vcell_client/api/admin_resource_api.py
pyvcell/_internal/api/vcell_client/api/bio_model_resource_api.py
pyvcell/_internal/api/vcell_client/api/field_data_resource_api.py
pyvcell/_internal/api/vcell_client/api/hello_world_api.py
pyvcell/_internal/api/vcell_client/api/publication_resource_api.py
pyvcell/_internal/api/vcell_client/api/simulation_resource_api.py
pyvcell/_internal/api/vcell_client/api/solver_resource_api.py
pyvcell/_internal/api/vcell_client/api/users_resource_api.py
pyvcell/_internal/api/vcell_client/api_client.py
pyvcell/_internal/api/vcell_client/api_response.py
pyvcell/_internal/api/vcell_client/auth/__init__.py
pyvcell/_internal/api/vcell_client/auth/auth_utils.py
pyvcell/_internal/api/vcell_client/configuration.py
pyvcell/_internal/api/vcell_client/docs/AccesTokenRepresentationRecord.md
pyvcell/_internal/api/vcell_client/docs/AdminResourceApi.md
pyvcell/_internal/api/vcell_client/docs/AnalyzedResultsFromFieldData.md
pyvcell/_internal/api/vcell_client/docs/BatchSystemType.md
pyvcell/_internal/api/vcell_client/docs/BioModel.md
pyvcell/_internal/api/vcell_client/docs/BioModelResourceApi.md
pyvcell/_internal/api/vcell_client/docs/BiomodelRef.md
pyvcell/_internal/api/vcell_client/docs/DataIdentifier.md
pyvcell/_internal/api/vcell_client/docs/DetailedState.md
pyvcell/_internal/api/vcell_client/docs/Domain.md
pyvcell/_internal/api/vcell_client/docs/Extent.md
pyvcell/_internal/api/vcell_client/docs/ExternalDataIdentifier.md
pyvcell/_internal/api/vcell_client/docs/FieldDataReference.md
pyvcell/_internal/api/vcell_client/docs/FieldDataResourceApi.md
pyvcell/_internal/api/vcell_client/docs/FieldDataSaveResults.md
pyvcell/_internal/api/vcell_client/docs/FieldDataShape.md
pyvcell/_internal/api/vcell_client/docs/HelloWorldApi.md
pyvcell-0.1.18.dist-info/LICENSE
pyvcell-0.1.18.dist-info/METADATA
pyvcell-0.1.18.dist-info/WHEEL
pyvcell-0.1.18.dist-info/RECORD
