Metadata-Version: 2.1
Name: pyvcell
Version: 0.1.18
Summary: This is the python wrapper for vcell modeling and simulation
Home-page: https://github.com/virtualcell/pyvcell
Author: Jim Schaff
Author-email: schaff@uchc.edu
Requires-Python: >=3.11,<4.0
Classifier: Programming Language :: Python :: 3
Classifier: Programming Language :: Python :: 3.11
Classifier: Programming Language :: Python :: 3.12
Requires-Dist: antimony (>=2.15.0,<3.0.0)
Requires-Dist: h5py (>=3.11.0,<4.0.0)
Requires-Dist: imageio (>=2.37.0,<3.0.0)
Requires-Dist: libvcell (>=0.0.13,<0.0.14)
Requires-Dist: lxml (>=5.3.1,<6.0.0)
Requires-Dist: matplotlib (>=3.10.0,<4.0.0)
Requires-Dist: numexpr (>=2.10.0,<3.0.0)
Requires-Dist: numpy (>=1.26.4,<3.0)
Requires-Dist: orjson (>=3.10.3,<4.0.0)
Requires-Dist: overrides (>=7.7.0,<8.0.0)
Requires-Dist: pydantic (>=2.10.5,<3.0.0)
Requires-Dist: python-dateutil (>=2.8.2,<3.0.0)
Requires-Dist: python-libsbml (>=5.20.4,<6.0.0)
Requires-Dist: pyvcell-fvsolver (>=0.1.1,<0.2.0)
Requires-Dist: pyvista (>=0.44.2,<0.45.0)
Requires-Dist: requests (>=2.32.3,<3.0.0)
Requires-Dist: requests-oauth2client (>=1.6.0,<2.0.0)
Requires-Dist: sympy (>=1.13.1,<2.0.0)
Requires-Dist: tensorstore (>=0.1.72,<0.2.0)
Requires-Dist: trame (>=3.8.1,<4.0.0)
Requires-Dist: trame-server (>=3.4.0,<4.0.0)
Requires-Dist: trame-vtk (>=2.8.15,<3.0.0)
Requires-Dist: trame-vuetify (>=2.8.1,<3.0.0)
Requires-Dist: typer (>=0.12.3,<1.0.0)
Requires-Dist: typing-extensions (>=4.12.2,<5.0.0)
Requires-Dist: urllib3 (>=2.3.0,<3.0.0)
Requires-Dist: vtk (>=9.3.1,<10.0.0)
Requires-Dist: zarr (>=2.17.2,<3.0.0)
Project-URL: Documentation, https://virtualcell.github.io/pyvcell/
Project-URL: Repository, https://github.com/virtualcell/pyvcell
